numfmt/__init__.py
numfmt/charmaps.py
numfmt/map.py
numfmt/intstr/__init__.py
numfmt/intstr/calc.py
numfmt/intstr/math.py
numfmt/intstr/standard.py
numfmt/intstr/utils.py
numfmt/scistr/__init__.py
numfmt/scistr/calc.py
numfmt/scistr/fracs.py
numfmt/scistr/ieee754.py
numfmt/scistr/standard.py
numfmt/scistr/utils.py
numfmt/utils/__init__.py
numfmt/utils/bitwise.py
numfmt/utils/floatwise.py
numfmt/utils/ftools.py
numfmt/utils/int.py
numfmt/utils/int_str.py
numfmt/utils/intwise.py
numfmt/utils/itools.py
NumFmt-0.0.0.post1.dist-info/LICENSE
NumFmt-0.0.0.post1.dist-info/METADATA
NumFmt-0.0.0.post1.dist-info/WHEEL
NumFmt-0.0.0.post1.dist-info/top_level.txt
NumFmt-0.0.0.post1.dist-info/RECORD
