Metadata-Version: 2.1
Name: NumFmt
Version: 0.0.0.post1
Summary: Format Numbers in Any Base and Charset
Home-page: https://github.com/technikker/numfmt
Author: technician
Author-email: <mail@xxxxxxxx.com>
License: MPL
Project-URL: Source, https://github.com/technikker/numfmt
Keywords: python,NumFmt,numfmt,number,format,formatter
Classifier: Development Status :: 2 - Pre-Alpha
Classifier: Intended Audience :: Developers
Classifier: License :: OSI Approved :: Mozilla Public License 2.0 (MPL 2.0)
Classifier: Programming Language :: Python :: 3
Classifier: Programming Language :: Python :: 3.6
Classifier: Programming Language :: Python :: 3.7
Classifier: Programming Language :: Python :: 3.8
Classifier: Programming Language :: Python :: 3.9
Classifier: Programming Language :: Python :: 3.10
Classifier: Programming Language :: Python :: 3.11
Classifier: Operating System :: OS Independent
Classifier: Topic :: Software Development :: Embedded Systems
Classifier: Topic :: Scientific/Engineering
Classifier: Topic :: Utilities
License-File: LICENSE
